{
  "unique_key": "stage2b:1899:https://www.highlandartstheatre.com/work-with-us",
  "url": "https://www.highlandartstheatre.com/work-with-us",
  "method": "GET",
  "payload": null,
  "headers": {},
  "user_data": {
    "__crawlee": {
      "maxRetries": 2,
      "state": 4
    },
    "source": {
      "record_id": "1899",
      "source_file": "found.csv",
      "source_row": "1900",
      "organization_name_original": "Highland Arts Theatre Association",
      "unresolved_q_identifier": "no",
      "input_website": "https://highlandartstheatre.com/",
      "final_website": "https://www.highlandartstheatre.com/",
      "canonical_website": "https://www.highlandartstheatre.com/",
      "normalized_domain": "highlandartstheatre.com",
      "original_status": "FOUND",
      "career_url": "https://www.highlandartstheatre.com/work-with-us",
      "link_text": "Work With Us",
      "score": "140",
      "ats_provider_detected": "",
      "evidence": "strong careers/jobs link text; careers/jobs URL path",
      "candidate_count": "3",
      "initial_classification": "likely_employer_career_page",
      "classification_reason": "Career-related link text or URL path",
      "retry_category": "",
      "recommended_next_action": "validate_page_and_extract_jobs",
      "processing_queue": "career_validation",
      "error": "",
      "organization_name_resolved": "",
      "ottawa_relationship": "",
      "ottawa_evidence": "",
      "validation_status": "unreviewed",
      "validation_notes": "",
      "last_processed": "2026-07-17",
      "checked_at_utc": "2026-07-17T22:53:22.266207+00:00",
      "requested_url": "https://www.highlandartstheatre.com/work-with-us",
      "loaded_url": "https://www.highlandartstheatre.com/work-with-us",
      "http_status": "200",
      "page_title": "Work With Us — The Highland Arts Theatre",
      "detected_ats": "",
      "jsonld_jobposting_count": "0",
      "probable_job_link_count": "0",
      "sample_job_links": "",
      "validation_result": "probable_career_page_needs_review",
      "validation_reason": "Career language detected, but job state is unclear",
      "body_text_sample": "SHOPPING FOR A COMEDY LOVER? UP NEXT: \n\nHOT FLASH COMEDY - JULY 31ST\n\n- CLICK HERE FOR TICKET INFO -\n\nSkip to Content\nWHAT'S ON\nGET INVOLVED\nLEARN MORE\nHAT ACADEMY\nDONATE\nTICKETS\nWORK WITH US\n\nAt the Highland Arts Theatre, we celebrate diversity and are committed to creating an inclusive environment for all employees. We encourage applications from candidates of all backgrounds and experiences.\n\nJoin us for an unforgettable season of storytelling and artistry as we bring compelling theatre to life\nin the heart of Cape Breton!\n\nScroll below for more information on our open positions:\n\nPatron Services Team Member (Casual Hours)\n\nPosition Title: Patron Services Staff Member\nLocation: Highland Arts Theatre, Sydney, Nova Scotia\nReports to: Patron Services Manager\n\nPOSITION OVERVIEW -\nThe Patron Services Staff Member plays a vital role in ensuring a smooth and enjoyable experience for patrons at the Highland Arts Theatre. This position involves working box office shifts, managing bar operations, maintaining cleanliness, and ensuring the theatre is well-prepared for performances. The ideal candidate is detail-oriented, organized, and passionate about providing exceptional customer service.\n\nKEY RESPONSIBILITIES -\n\nBox Office Duties:\n Handle ticket bookings via phone, email, and in person.\n Assist patrons with ticket inquiries, exchanges, and purchases.\n Provide excellent customer service to all patrons, resolving issues promptly.\n Maintain accurate records of transactions and ti",
      "crawl_error": "",
      "stage2_checked_at_utc": "2026-07-18T15:33:13.936600+00:00",
      "stage2_result": "confirmed_career_landing_unresolved",
      "stage2_reason": "Valid career landing page; downstream job source not resolved",
      "resolved_monitor_url": "https://www.highlandartstheatre.com/work-with-us",
      "resolved_ats": "",
      "stage2_jsonld_jobposting_count": "0",
      "stage2_probable_job_link_count": "0",
      "stage2_sample_job_links": "",
      "candidate_urls_found": "",
      "candidate_visits_json": "[]",
      "stage2_error": ""
    }
  },
  "retry_count": 0,
  "no_retry": false,
  "loaded_url": null,
  "handled_at": "2026-07-19 02:37:27.151504+00:00"
}