{
  "unique_key": "stage2b:4399:https://www.sabaithaicuisine.ca/jobs",
  "url": "https://www.sabaithaicuisine.ca/jobs",
  "method": "GET",
  "payload": null,
  "headers": {},
  "user_data": {
    "__crawlee": {
      "maxRetries": 2,
      "state": 4
    },
    "source": {
      "record_id": "4399",
      "source_file": "found.csv",
      "source_row": "4400",
      "organization_name_original": "Sabai Thai Cuisine",
      "unresolved_q_identifier": "no",
      "input_website": "https://sabaithaicuisine.ca/",
      "final_website": "https://www.sabaithaicuisine.ca/",
      "canonical_website": "https://www.sabaithaicuisine.ca/",
      "normalized_domain": "sabaithaicuisine.ca",
      "original_status": "FOUND",
      "career_url": "https://www.sabaithaicuisine.ca/jobs",
      "link_text": "JOBS",
      "score": "140",
      "ats_provider_detected": "",
      "evidence": "strong careers/jobs link text; careers/jobs URL path",
      "candidate_count": "1",
      "initial_classification": "likely_employer_career_page",
      "classification_reason": "Career-related link text or URL path",
      "retry_category": "",
      "recommended_next_action": "validate_page_and_extract_jobs",
      "processing_queue": "career_validation",
      "error": "",
      "organization_name_resolved": "",
      "ottawa_relationship": "",
      "ottawa_evidence": "",
      "validation_status": "unreviewed",
      "validation_notes": "",
      "last_processed": "2026-07-17",
      "checked_at_utc": "2026-07-18T02:04:58.111509+00:00",
      "requested_url": "https://www.sabaithaicuisine.ca/jobs",
      "loaded_url": "https://www.sabaithaicuisine.ca/jobs",
      "http_status": "200",
      "page_title": "JOBS — Sabai Thai Cuisine",
      "detected_ats": "",
      "jsonld_jobposting_count": "0",
      "probable_job_link_count": "0",
      "sample_job_links": "",
      "validation_result": "probable_career_page_needs_review",
      "validation_reason": "Career language detected, but job state is unclear",
      "body_text_sample": "HOME\n \nABOUT\n \nLUNCH MENU\n \nDINNER MENU\n \nCATERING\n \nRESERVATIONS\n \nCONTACT US\n \nJOBS\nLOOKING TO WORK WITH US?\nName\nFirst Name\n(required)\nLast Name\n(required)\nEmail\n(required)\nSign up for news and updates\nSubject\n(required)\nMessage\n(required)\nFile Upload\nAdd a File\nSubmit\nSABAI THAI CUISINE, 4055 CARLING AVENUE, OTTAWA, ON, K2K 2A4, CANADA613-271-8885\n\nPowered by Squarespace\n\nORDER ONLINE FOR PICK UP\nORDER NOW",
      "crawl_error": "",
      "stage2_checked_at_utc": "2026-07-18T16:54:06.541297+00:00",
      "stage2_result": "confirmed_career_landing_unresolved",
      "stage2_reason": "Valid career landing page; downstream job source not resolved",
      "resolved_monitor_url": "https://www.sabaithaicuisine.ca/jobs",
      "resolved_ats": "",
      "stage2_jsonld_jobposting_count": "0",
      "stage2_probable_job_link_count": "0",
      "stage2_sample_job_links": "",
      "candidate_urls_found": "60:https://www.sabaithaicuisine.ca/jobs",
      "candidate_visits_json": "[]",
      "stage2_error": ""
    }
  },
  "retry_count": 0,
  "no_retry": false,
  "loaded_url": null,
  "handled_at": "2026-07-19 04:40:08.578120+00:00"
}