{
  "unique_key": "stage2b:4101:https://cvcfoundation.org/about/careers/",
  "url": "https://cvcfoundation.org/about/careers/",
  "method": "GET",
  "payload": null,
  "headers": {},
  "user_data": {
    "__crawlee": {
      "maxRetries": 2,
      "state": 4
    },
    "source": {
      "record_id": "4101",
      "source_file": "found.csv",
      "source_row": "4102",
      "organization_name_original": "Q137366434",
      "unresolved_q_identifier": "yes",
      "input_website": "https://cvcfoundation.org/",
      "final_website": "https://cvcfoundation.org/",
      "canonical_website": "https://cvcfoundation.org/",
      "normalized_domain": "cvcfoundation.org",
      "original_status": "FOUND",
      "career_url": "https://cvcfoundation.org/about/careers/",
      "link_text": "Careers",
      "score": "140",
      "ats_provider_detected": "",
      "evidence": "strong careers/jobs link text; careers/jobs URL path",
      "candidate_count": "3",
      "initial_classification": "likely_employer_career_page",
      "classification_reason": "Career-related link text or URL path",
      "retry_category": "",
      "recommended_next_action": "validate_page_and_extract_jobs",
      "processing_queue": "career_validation",
      "error": "",
      "organization_name_resolved": "",
      "ottawa_relationship": "",
      "ottawa_evidence": "",
      "validation_status": "unreviewed",
      "validation_notes": "",
      "last_processed": "2026-07-17",
      "checked_at_utc": "2026-07-18T01:32:25.112961+00:00",
      "requested_url": "https://cvcfoundation.org/about/careers/",
      "loaded_url": "https://cvcfoundation.org/about/careers/",
      "http_status": "200",
      "page_title": "Careers - Comox Valley Community Foundation",
      "detected_ats": "",
      "jsonld_jobposting_count": "0",
      "probable_job_link_count": "0",
      "sample_job_links": "",
      "validation_result": "probable_career_page_needs_review",
      "validation_reason": "Career language detected, but job state is unclear",
      "body_text_sample": "Explore WAYS TO GIVE and DONATE online today.\n\nHome\nContact\nOffice: (250) 338-8444\nGiving\nCommunity Impact\nGrant Opportunities\nCommunity Loans\nAdvisors\nAbout\nDonate Online\nCareers\nTHERE ARE NO CURRENT OPPORTUNITIES.\n\nThe Comox Valley Community Foundation has served the Comox Valley since 1996. We work to bring together the generosity of donors with the ideas and energy of charities and communities across the Comox Valley. Join us and start making a difference in our community.\n\nWhy the Comox Valley?\n\nThe Comox Valley is considered one of the most desirable places to live in Canada due to its incredible natural setting on the Salish Sea, mild climate and limitless year-round recreational pursuits. An outdoor adventure and culinary destination, you can ski with an ocean view, swim in crystal clear waters, mountain bike or hike along one of the many river systems, paddle the many kilometres of stunning shoreline, or tee off at one of many scenic golf courses. The Comox Valley is also renowned for its many cultural, art, music, and food festivals.\n\nWhy the Comox Valley Community Foundation?\n\nCVCF is an equal opportunity organization and encourages interest from equity deserving individuals, women, youth, individuals with disabilities, and all other qualified applicants. We welcome you to inform us, in confidence, if you require any special accommodations to participate in our recruitment process.\n\nWe are humbled to live and work on the unceded, traditional territory of the K՗mok",
      "crawl_error": "",
      "stage2_checked_at_utc": "2026-07-18T16:40:32.645037+00:00",
      "stage2_result": "confirmed_career_landing_unresolved",
      "stage2_reason": "Valid career landing page; downstream job source not resolved",
      "resolved_monitor_url": "https://cvcfoundation.org/about/careers/",
      "resolved_ats": "",
      "stage2_jsonld_jobposting_count": "0",
      "stage2_probable_job_link_count": "0",
      "stage2_sample_job_links": "",
      "candidate_urls_found": "60:https://cvcfoundation.org/about/careers/",
      "candidate_visits_json": "[]",
      "stage2_error": ""
    }
  },
  "retry_count": 0,
  "no_retry": false,
  "loaded_url": null,
  "handled_at": "2026-07-19 04:19:07.970277+00:00"
}