{
  "unique_key": "stage2b:797:https://www.canadianstage.com/about/jobs",
  "url": "https://www.canadianstage.com/about/jobs",
  "method": "GET",
  "payload": null,
  "headers": {},
  "user_data": {
    "__crawlee": {
      "maxRetries": 2,
      "state": 6
    },
    "source": {
      "record_id": "797",
      "source_file": "found.csv",
      "source_row": "798",
      "organization_name_original": "Canadian Stage",
      "unresolved_q_identifier": "no",
      "input_website": "https://canadianstage.com/",
      "final_website": "https://www.canadianstage.com/",
      "canonical_website": "https://www.canadianstage.com/",
      "normalized_domain": "canadianstage.com",
      "original_status": "FOUND",
      "career_url": "https://www.canadianstage.com/about/jobs",
      "link_text": "Work with Us",
      "score": "140",
      "ats_provider_detected": "",
      "evidence": "strong careers/jobs link text; careers/jobs URL path",
      "candidate_count": "2",
      "initial_classification": "likely_employer_career_page",
      "classification_reason": "Career-related link text or URL path",
      "retry_category": "",
      "recommended_next_action": "validate_page_and_extract_jobs",
      "processing_queue": "career_validation",
      "error": "",
      "organization_name_resolved": "",
      "ottawa_relationship": "",
      "ottawa_evidence": "",
      "validation_status": "unreviewed",
      "validation_notes": "",
      "last_processed": "2026-07-17",
      "checked_at_utc": "2026-07-17T21:55:10.671620+00:00",
      "requested_url": "https://www.canadianstage.com/about/jobs",
      "loaded_url": "https://www.canadianstage.com/about/jobs",
      "http_status": "200",
      "page_title": "Work With Us / Canadian Stage",
      "detected_ats": "",
      "jsonld_jobposting_count": "0",
      "probable_job_link_count": "0",
      "sample_job_links": "",
      "validation_result": "probable_career_page_needs_review",
      "validation_reason": "Career language detected, but job state is unclear",
      "body_text_sample": "Skip to content\nMy Account\nDonate Now\nBuy Tickets\nAbout\nShows & Events\nSubscribe\nPlan Your Visit\nArtists @ CS\nSupport Us\nWork with Us\n\nCome join Canada’s leading contemporary performing arts organization as we create a collision of disciplines and cultures reflecting the dynamism and complexity of Canada. Be part of a vital artistic force locally, nationally, and internationally.\n\nPeople - We respect and celebrate the potential in everyone.\n\nBelonging - We create spaces where everyone feels welcome and can connect.\n\nCuriosity - We welcome different perspectives and embrace the endless possibilities of storytelling.\n\nCraft - We are dedicated to excellence in everything we do and support the collaborative, creative process of making live theatre.\n\nAt Canadian Stage we seek to hire individuals who share these values. We value the diversity of people and communities we serve and are committed to equity and inclusion in all our operations.\n\nIf you require accommodation with the application process, please contact hr@canadianstage.com.\n\n \n\nJoin Our Mailing List\n\nFind Out First! Sign Up for Canadian Stage Emails\n\nFirst Name\nLast Name\nEmail\nSign Up\n26 Berkeley Street,\nToronto, ON, M5A 2W3\n\nBox Office: 416.368.3110\nboxoffice[at]canadianstage.com\nAdmin: 416.367.8243\n\nMonday - Friday: 12pm - 5pm\nSaturday & Sunday: Closed\n\nAbout\n\nAbout Canadian Stage\nOur People\nContact Us\nWork with Us\nVolunteer Opportunities\nRent Our Spaces\nPast Productions\n\nShows & Events\n\n26.27 Season\nDream in High Par",
      "crawl_error": "",
      "stage2_checked_at_utc": "2026-07-18T15:06:44.860774+00:00",
      "stage2_result": "confirmed_career_landing_unresolved",
      "stage2_reason": "Valid career landing page; downstream job source not resolved",
      "resolved_monitor_url": "https://www.canadianstage.com/about/jobs",
      "resolved_ats": "",
      "stage2_jsonld_jobposting_count": "0",
      "stage2_probable_job_link_count": "0",
      "stage2_sample_job_links": "",
      "candidate_urls_found": "60:https://www.canadianstage.com/about/jobs#content",
      "candidate_visits_json": "[]",
      "stage2_error": ""
    }
  },
  "retry_count": 2,
  "no_retry": false,
  "loaded_url": "https://www.canadianstage.com/about/jobs",
  "handled_at": "2026-07-19 06:37:50.479731+00:00"
}