{
  "unique_key": "stage2b:2369:https://lmrlawyers.com/our-firm/careers/",
  "url": "https://lmrlawyers.com/our-firm/careers/",
  "method": "GET",
  "payload": null,
  "headers": {},
  "user_data": {
    "__crawlee": {
      "maxRetries": 2,
      "state": 4
    },
    "source": {
      "record_id": "2369",
      "source_file": "found.csv",
      "source_row": "2370",
      "organization_name_original": "Low Murchison Radnoff LLP",
      "unresolved_q_identifier": "no",
      "input_website": "https://lmrlawyers.com/",
      "final_website": "https://lmrlawyers.com/",
      "canonical_website": "https://lmrlawyers.com/",
      "normalized_domain": "lmrlawyers.com",
      "original_status": "FOUND",
      "career_url": "https://lmrlawyers.com/our-firm/careers/",
      "link_text": "Careers",
      "score": "140",
      "ats_provider_detected": "",
      "evidence": "strong careers/jobs link text; careers/jobs URL path",
      "candidate_count": "1",
      "initial_classification": "likely_employer_career_page",
      "classification_reason": "Career-related link text or URL path",
      "retry_category": "",
      "recommended_next_action": "validate_page_and_extract_jobs",
      "processing_queue": "career_validation",
      "error": "",
      "organization_name_resolved": "",
      "ottawa_relationship": "",
      "ottawa_evidence": "",
      "validation_status": "unreviewed",
      "validation_notes": "",
      "last_processed": "2026-07-17",
      "checked_at_utc": "2026-07-17T23:18:53.981259+00:00",
      "requested_url": "https://lmrlawyers.com/our-firm/careers/",
      "loaded_url": "https://lmrlawyers.com/our-firm/careers/",
      "http_status": "200",
      "page_title": "Careers | LMR Lawyers | Work at Low Murchison Radnoff LLP",
      "detected_ats": "",
      "jsonld_jobposting_count": "0",
      "probable_job_link_count": "0",
      "sample_job_links": "",
      "validation_result": "probable_career_page_needs_review",
      "validation_reason": "Career language detected, but job state is unclear",
      "body_text_sample": "Please note: This website includes an accessibility system. Press Control-F11 to adjust the website to the visually impaired who are using a screen reader; Press Control-F10 to open an accessibility menu.\nAccessibility\nPress enter for Accessibility for blind people\nwho use screen readers\nPress enter for Keyboard Navigation\nPress enter for Accessibility menu\nLEGAL SERVICES\nBusiness Law\nCivil Litigation\nConstruction Law\nEmployment and Labour Law\nEstates and Succession\nFamily Law\nInstitutional Law\nReal Estate\nPersonal Injury\nTechnology Law\nOUR TEAM\nOUR STORY\nCAREERS\nARTICLING AT LMR\nBLOG\nNEWSLETTER\nCONTACT US\nFR\nFR\nContact Us\n(613) 236‑9442\nJOIN OUR\nTEAM\n\nIt takes a special kind of person to work at Low Murchison Radnoff LLP. Somebody whose experience and determination are only matched by their strong client relations skills. Think you’d fit in well here?\n\nPlease view our current opportunities below.\n\nArticling at LMR\n\nPROFESSIONAL OPPORTUNITIES\nREAL ESTATE LAWYER\n\nIn this new role, Low Murchison Radnoff LLP is seeking an Associate Lawyer with 3-5 years’ experience in real estate transactions to join our firm in order to more fully meet the needs of its growing clientele. We are looking for a solicitor who can assist our clients as they structure and negotiate their projects– creatively, effectively and professionally.\n\nQualifications:\n\nExperience in residential real estate transactions.\nExperience in commercial law, building and development, builder sales, and estate planning w",
      "crawl_error": "",
      "stage2_checked_at_utc": "2026-07-18T15:44:18.493594+00:00",
      "stage2_result": "confirmed_career_landing_unresolved",
      "stage2_reason": "Valid career landing page; downstream job source not resolved",
      "resolved_monitor_url": "https://lmrlawyers.com/our-firm/careers/",
      "resolved_ats": "",
      "stage2_jsonld_jobposting_count": "0",
      "stage2_probable_job_link_count": "0",
      "stage2_sample_job_links": "",
      "candidate_urls_found": "115:https://lmrlawyers.com/our-firm/careers/ | 60:https://lmrlawyers.com/services/employment-and-labour-law-group/",
      "candidate_visits_json": "[{\"url\": \"https://lmrlawyers.com/services/employment-and-labour-law-group/\", \"result\": \"confirmed_career_landing_unresolved\", \"ats\": \"\", \"score\": 60}]",
      "stage2_error": ""
    }
  },
  "retry_count": 0,
  "no_retry": false,
  "loaded_url": null,
  "handled_at": "2026-07-19 03:00:47.808551+00:00"
}