{
  "unique_key": "stage2b:3680:https://millcreekcarecentre.ca/join-our-team/",
  "url": "https://millcreekcarecentre.ca/join-our-team/",
  "method": "GET",
  "payload": null,
  "headers": {},
  "user_data": {
    "__crawlee": {
      "maxRetries": 2,
      "state": 6
    },
    "source": {
      "record_id": "3680",
      "source_file": "found.csv",
      "source_row": "3681",
      "organization_name_original": "Q137365564",
      "unresolved_q_identifier": "yes",
      "input_website": "https://millcreekcarecentre.ca/",
      "final_website": "https://millcreekcarecentre.ca/",
      "canonical_website": "https://millcreekcarecentre.ca/",
      "normalized_domain": "millcreekcarecentre.ca",
      "original_status": "FOUND",
      "career_url": "https://millcreekcarecentre.ca/join-our-team/",
      "link_text": "Join Our Team",
      "score": "140",
      "ats_provider_detected": "",
      "evidence": "strong careers/jobs link text; careers/jobs URL path",
      "candidate_count": "5",
      "initial_classification": "likely_employer_career_page",
      "classification_reason": "Career-related link text or URL path",
      "retry_category": "",
      "recommended_next_action": "validate_page_and_extract_jobs",
      "processing_queue": "career_validation",
      "error": "",
      "organization_name_resolved": "",
      "ottawa_relationship": "",
      "ottawa_evidence": "",
      "validation_status": "unreviewed",
      "validation_notes": "",
      "last_processed": "2026-07-17",
      "checked_at_utc": "2026-07-18T00:37:10.217274+00:00",
      "requested_url": "https://millcreekcarecentre.ca/join-our-team/",
      "loaded_url": "https://millcreekcarecentre.ca/join-our-team/",
      "http_status": "200",
      "page_title": "Join Our Team - Mill Creek Care Centre",
      "detected_ats": "",
      "jsonld_jobposting_count": "0",
      "probable_job_link_count": "0",
      "sample_job_links": "",
      "validation_result": "probable_career_page_needs_review",
      "validation_reason": "Career language detected, but job state is unclear",
      "body_text_sample": "Close panel\nFont resize\nA-\nA+\nReset font size\nKeyboard navigation\nReadable font\nClear\nClose panel\nAccessibility by WAH\nSkip to content\n(705) 719-6222\n\n286 Hurst Drive Barrie, ON\nDonate Now\nBook a Tour\nGet Directions\nSubmit an Inquiry\nGracious Adult Living\nAbout Long Term Care\nChoosing a Home\nAdmission Process\nOntario Health atHome\nAdmission FAQs\nRegulations\nAbout Us\nOur Commitment\nAccommodations\nQuality of Care\nOur Team\nResident & Family Councils\nBook a Tour\nServices\nPersonal Care Services\nSpecialized Services\nResident Programs\nSignature Programs\nCulinary Services\nHelping You\nFamily Corner\nFrequently Asked Questions\nLinks\nJoin Our Team\nJoin Our Team\nVolunteers\nCareers\nCharitable Donations\nTeam Resources\nContact Information\nLocation\nSubmit an Inquiry\nJoin Our Team\n\nWe are responsible on a daily basis for the health and well-being of our long term care residents. We seek people who share our values – who have the integrity to do the right thing, a passion for this important work, and a commitment to teamwork and shared success.\n\nFamilies have relied on us to provide competent and compassionate care for their loved ones. We enjoy this excellent reputation thanks to the team spirit and dedication of our employees at every level. We are equally committed to giving the best to our employees, providing competitive salaries and benefit packages along with supporting educational opportunities for professional growth.\n\nAs an employer, we protect our employees’ privacy by providing stri",
      "crawl_error": "",
      "stage2_checked_at_utc": "2026-07-18T16:24:06.694268+00:00",
      "stage2_result": "confirmed_career_landing_unresolved",
      "stage2_reason": "Valid career landing page; downstream job source not resolved",
      "resolved_monitor_url": "https://millcreekcarecentre.ca/join-our-team/",
      "resolved_ats": "",
      "stage2_jsonld_jobposting_count": "0",
      "stage2_probable_job_link_count": "0",
      "stage2_sample_job_links": "",
      "candidate_urls_found": "115:https://millcreekcarecentre.ca/join-our-team/careers/ | 60:https://millcreekcarecentre.ca/wp-content/uploads/sites/17/2020/11/Employment-application.doc",
      "candidate_visits_json": "[{\"url\": \"https://millcreekcarecentre.ca/join-our-team/careers/\", \"result\": \"confirmed_career_landing_unresolved\", \"ats\": \"\", \"score\": 115}, {\"url\": \"https://millcreekcarecentre.ca/wp-content/uploads/sites/17/2020/11/Employment-application.doc\", \"result\": \"candidate_visit_failed\", \"ats\": \"\", \"score\": 60, \"error\": \"Error: Page.goto: Download is starting\\nCall log:\\n  - navigating to \\\"https://millcreekcarecentre.ca/wp-content/uploads/sites/17/2020/11/Employment-application.doc\\\", waiting until \\\"domcontentloaded\\\"\\n\"}]",
      "stage2_error": ""
    }
  },
  "retry_count": 2,
  "no_retry": false,
  "loaded_url": "https://millcreekcarecentre.ca/join-our-team/",
  "handled_at": "2026-07-19 07:10:41.899952+00:00"
}