{
  "unique_key": "stage2b:3700:https://www.pinecreeksd.mb.ca/parents/careers_and_technology_studies",
  "url": "https://www.pinecreeksd.mb.ca/parents/careers_and_technology_studies",
  "method": "GET",
  "payload": null,
  "headers": {},
  "user_data": {
    "__crawlee": {
      "maxRetries": 2,
      "state": 4
    },
    "source": {
      "record_id": "3700",
      "source_file": "found.csv",
      "source_row": "3701",
      "organization_name_original": "Q137365643",
      "unresolved_q_identifier": "yes",
      "input_website": "https://pinecreeksd.mb.ca/",
      "final_website": "https://www.pinecreeksd.mb.ca/",
      "canonical_website": "https://www.pinecreeksd.mb.ca/",
      "normalized_domain": "pinecreeksd.mb.ca",
      "original_status": "FOUND",
      "career_url": "https://www.pinecreeksd.mb.ca/parents/careers_and_technology_studies",
      "link_text": "Careers and Technology Studies",
      "score": "80",
      "ats_provider_detected": "",
      "evidence": "strong careers/jobs link text",
      "candidate_count": "3",
      "initial_classification": "likely_employer_career_page",
      "classification_reason": "Career-related link text or URL path",
      "retry_category": "",
      "recommended_next_action": "validate_page_and_extract_jobs",
      "processing_queue": "career_validation",
      "error": "",
      "organization_name_resolved": "",
      "ottawa_relationship": "",
      "ottawa_evidence": "",
      "validation_status": "unreviewed",
      "validation_notes": "",
      "last_processed": "2026-07-17",
      "checked_at_utc": "2026-07-18T00:39:27.701579+00:00",
      "requested_url": "https://www.pinecreeksd.mb.ca/parents/careers_and_technology_studies",
      "loaded_url": "https://www.pinecreeksd.mb.ca/parents/careers_and_technology_studies",
      "http_status": "200",
      "page_title": "Careers and Technology Studies - Pine Creek School Division",
      "detected_ats": "",
      "jsonld_jobposting_count": "0",
      "probable_job_link_count": "0",
      "sample_job_links": "",
      "validation_result": "probable_career_page_needs_review",
      "validation_reason": "Career language detected, but job state is unclear",
      "body_text_sample": "Skip navigation\nLanguage\nPublished Links\nLogin\nPINE CREEK SCHOOL DIVISION\nLearning for Living\nHome\nGovernance\nDivision\nSchools\nStaff\nParents\nEmployment\nRegistration\nSkip Sidebar Navigation\nParents\nCareers and Technology Studies\nK - 8\nHigh School Apprenticeship Program (hsap)\nPine Creek School Division / Parents / Careers and Technology Studies\nCareers and Technology Studies\n\nCAREER DEVELOPMENT\n\nMy Blueprint is available for all students in Pine Creek School Division\n\n \n\nELEMENTARY SCHOOL\n\n\t\n\nMIDDLE YEARS\n\n\t\n\nHIGH SCHOOL\n\n\n\n\nCareer Development can begin at an early age. Children need to explore about themselves to learn what interests them.\n\n\t\n\nMiddle Years students begin exploring possible job futures in more detail by matching their learning styles, interests, personality,and strengths to careers that suit them.\n\n\t\n\nFiguring out what you want to do post-secondary is not easy. MyBlueprint offers comprehensive tools to help students plan a future.\n\n\n\n\nALL ABOUT ME\n\n\t\n\nMY BLUEPRINT\n\n\t\n\nEDUCATION PLANNER\n\n\n\n\nKnowing about yourself and the things you like is a good start to making matches to a career that suits you.All About Me, the companion program to the the career planner tool used in Grades 7-12 is a visual portfolio allows students to explore their interests to learn more about themselves and possible future careers.\n\n\t\n\nTheEducation Planner from myBlueprint is a career planning tool that is available to Grade 7-12 students in Pine Creek School Division. Middle Years studen",
      "crawl_error": "",
      "stage2_checked_at_utc": "2026-07-18T16:25:34.920048+00:00",
      "stage2_result": "confirmed_career_landing_unresolved",
      "stage2_reason": "Valid career landing page; downstream job source not resolved",
      "resolved_monitor_url": "https://www.pinecreeksd.mb.ca/parents/careers_and_technology_studies",
      "resolved_ats": "",
      "stage2_jsonld_jobposting_count": "0",
      "stage2_probable_job_link_count": "0",
      "stage2_sample_job_links": "",
      "candidate_urls_found": "115:https://www.pinecreeksd.mb.ca/parents/careers_and_technology_studies | 115:https://www.pinecreeksd.mb.ca/parents/careers_and_technology_studies/ | 60:https://www.pinecreeksd.mb.ca/employment",
      "candidate_visits_json": "[{\"url\": \"https://www.pinecreeksd.mb.ca/parents/careers_and_technology_studies\", \"result\": \"confirmed_career_landing_unresolved\", \"ats\": \"\", \"score\": 115}, {\"url\": \"https://www.pinecreeksd.mb.ca/employment\", \"result\": \"needs_manual_review\", \"ats\": \"\", \"score\": 60}]",
      "stage2_error": ""
    }
  },
  "retry_count": 0,
  "no_retry": false,
  "loaded_url": null,
  "handled_at": "2026-07-19 04:04:32.241731+00:00"
}